pydukeenergy
