Metadata-Version: 1.0
Name: pydukeenergy
Version: 0.0.6
Summary: Interface to the unofficial Duke Energy API
Home-page: http://github.com/w1ll1am23/pyduke-energy
Author: William Scanlon
Author-email: UNKNOWN
License: MIT
Platform: UNKNOWN
